odoo/addons/stock_reception_screen_qty_by_packaging/README.rst
odoo/addons/stock_reception_screen_qty_by_packaging/__init__.py
odoo/addons/stock_reception_screen_qty_by_packaging/__manifest__.py
odoo/addons/stock_reception_screen_qty_by_packaging/i18n/es_AR.po
odoo/addons/stock_reception_screen_qty_by_packaging/i18n/it.po
odoo/addons/stock_reception_screen_qty_by_packaging/i18n/pt_BR.po
odoo/addons/stock_reception_screen_qty_by_packaging/i18n/stock_reception_screen_qty_by_packaging.pot
odoo/addons/stock_reception_screen_qty_by_packaging/readme/CONTRIBUTORS.rst
odoo/addons/stock_reception_screen_qty_by_packaging/readme/CREDITS.rst
odoo/addons/stock_reception_screen_qty_by_packaging/readme/DESCRIPTION.rst
odoo/addons/stock_reception_screen_qty_by_packaging/static/description/icon.png
odoo/addons/stock_reception_screen_qty_by_packaging/static/description/index.html
odoo/addons/stock_reception_screen_qty_by_packaging/views/stock_reception_screen.xml
odoo14_addon_stock_reception_screen_qty_by_packaging-14.0.1.1.1.dev4.dist-info/METADATA
odoo14_addon_stock_reception_screen_qty_by_packaging-14.0.1.1.1.dev4.dist-info/WHEEL
odoo14_addon_stock_reception_screen_qty_by_packaging-14.0.1.1.1.dev4.dist-info/top_level.txt
odoo14_addon_stock_reception_screen_qty_by_packaging-14.0.1.1.1.dev4.dist-info/RECORD
